{
    "1": {
        "task_type": "prosaccade",
        "game_type": "gap",
        "target_position": [
            739,
            893
        ],
        "trial_start_time": 1742412664.047371,
        "stimulus_onset_time": 1742412668.257768,
        "trial_end_time": 1742412676.262576
    },
    "2": {
        "task_type": "antisaccade",
        "game_type": "gap",
        "target_position": [
            51,
            433
        ],
        "trial_start_time": 1742412676.767775,
        "stimulus_onset_time": 1742412680.977909,
        "trial_end_time": 1742412688.992254
    },
    "3": {
        "task_type": "prosaccade",
        "game_type": "overlap",
        "target_position": [
            739,
            33
        ],
        "trial_start_time": 1742412689.49725,
        "stimulus_onset_time": 1742412693.504837,
        "trial_end_time": 1742412701.913715
    },
    "4": {
        "task_type": "antisaccade",
        "game_type": "overlap",
        "target_position": [
            1468,
            433
        ],
        "trial_start_time": 1742412702.4187992,
        "stimulus_onset_time": 1742412706.423848,
        "trial_end_time": 1742412714.832442
    },
    "summary": {
        "prosaccade-gap": {
            "Total_number_of_trials": "1.000",
            "saccade_omission_percentage (%)": "0.000",
            "average_reaction_time (ms)": "27.531",
            "average_saccade_duration (ms)": "94.791",
            "saccade_error_percentage (%)": "0.000",
            "average_fixation_duration (ms)": "419.304"
        },
        "prosaccade-overlap": {
            "Total_number_of_trials": "1.000",
            "saccade_omission_percentage (%)": "0.000",
            "average_reaction_time (ms)": "46.769",
            "average_saccade_duration (ms)": "20.389",
            "saccade_error_percentage (%)": "0.000",
            "average_fixation_duration (ms)": "235.007"
        },
        "antisaccade-gap": {
            "Total_number_of_trials": "1.000",
            "saccade_omission_percentage (%)": "0.000",
            "average_reaction_time (ms)": "31.012",
            "average_saccade_duration (ms)": "40.577",
            "saccade_error_percentage (%)": "0.000",
            "average_fixation_duration (ms)": "392.550"
        },
        "antisaccade-overlap": {
            "Total_number_of_trials": "1.000",
            "saccade_omission_percentage (%)": "0.000",
            "average_reaction_time (ms)": "48.386",
            "average_saccade_duration (ms)": "41.209",
            "saccade_error_percentage (%)": "0.000",
            "average_fixation_duration (ms)": "298.761"
        }
    }
}